pyclesperanto_assistant/__init__.py
pyclesperanto_assistant/ipython/__init__.py
pyclesperanto_assistant-0.1.1.dist-info/LICENSE
pyclesperanto_assistant-0.1.1.dist-info/METADATA
pyclesperanto_assistant-0.1.1.dist-info/WHEEL
pyclesperanto_assistant-0.1.1.dist-info/top_level.txt
pyclesperanto_assistant-0.1.1.dist-info/RECORD
