Metadata-Version: 2.1
Name: pyclesperanto-assistant
Version: 0.1.1
Summary: Assistant for pyclesperanto scripting
Home-page: https://github.com/clEsperanto/pyclesperanto_assistant
Author: haesleinhuepf
Author-email: robert.haase@tu-dresden.de
License: UNKNOWN
Platform: UNKNOWN
Classifier: Programming Language :: Python :: 3
Classifier: License :: OSI Approved :: BSD License
Classifier: Operating System :: OS Independent
Classifier: Intended Audience :: Science/Research
Classifier: Development Status :: 3 - Alpha
Requires-Python: >=3.6
License-File: LICENSE
Requires-Dist: pyclesperanto-assistant
